faker_ai/__init__.py
faker_ai/provider.py
faker_ai_provider-1.0.2.dist-info/licenses/LICENSE
tests/test_provider.py
faker_ai_provider-1.0.2.dist-info/METADATA
faker_ai_provider-1.0.2.dist-info/WHEEL
faker_ai_provider-1.0.2.dist-info/top_level.txt
faker_ai_provider-1.0.2.dist-info/RECORD
