Metadata-Version: 2.4
Name: faker-ai-provider
Version: 1.0.2
Summary: Generate realistic AI/ML test data: 65+ models, 45+ companies, 25+ frameworks, 30+ datasets, architectures, tasks, and parameters
License: MIT
Project-URL: Homepage, https://github.com/rodrigobnogueira/faker-ai
Project-URL: Repository, https://github.com/rodrigobnogueira/faker-ai
Keywords: faker,ai,ml,machine-learning,fake-data,testing
Classifier: Development Status :: 4 - Beta
Classifier: Intended Audience :: Developers
Classifier: License :: OSI Approved :: MIT License
Classifier: Programming Language :: Python :: 3
Classifier: Programming Language :: Python :: 3.10
Classifier: Programming Language :: Python :: 3.11
Classifier: Programming Language :: Python :: 3.12
Classifier: Programming Language :: Python :: 3.13
Requires-Python: >=3.10
License-File: LICENSE
Requires-Dist: faker>=18.0.0
Dynamic: license-file
